market_tickers/__init__.py
market_tickers/core.py
market_tickers/loaders.py
market_tickers/data/currencies/currencies.csv
market_tickers/data/etfs/etfs.csv
market_tickers/data/indices/indices.csv
market_tickers/data/stocks/stocks_argentina.csv
market_tickers/data/stocks/stocks_australia.csv
market_tickers/data/stocks/stocks_austria.csv
market_tickers/data/stocks/stocks_belgium.csv
market_tickers/data/stocks/stocks_brazil.csv
market_tickers/data/stocks/stocks_canada.csv
market_tickers/data/stocks/stocks_china.csv
market_tickers/data/stocks/stocks_denmark.csv
market_tickers/data/stocks/stocks_estonia.csv
market_tickers/data/stocks/stocks_finland.csv
market_tickers/data/stocks/stocks_france.csv
market_tickers/data/stocks/stocks_germany.csv
market_tickers/data/stocks/stocks_greece.csv
market_tickers/data/stocks/stocks_hong_kong.csv
market_tickers/data/stocks/stocks_iceland.csv
market_tickers/data/stocks/stocks_india.csv
market_tickers/data/stocks/stocks_indonesia.csv
market_tickers/data/stocks/stocks_ireland.csv
market_tickers/data/stocks/stocks_israel.csv
market_tickers/data/stocks/stocks_italy.csv
market_tickers/data/stocks/stocks_latvia.csv
market_tickers/data/stocks/stocks_lithuania.csv
market_tickers/data/stocks/stocks_malaysia.csv
market_tickers/data/stocks/stocks_mexico.csv
market_tickers/data/stocks/stocks_netherlands.csv
market_tickers/data/stocks/stocks_new_zealand.csv
market_tickers/data/stocks/stocks_norway.csv
market_tickers/data/stocks/stocks_portugal.csv
market_tickers/data/stocks/stocks_qatar.csv
market_tickers/data/stocks/stocks_russia.csv
market_tickers/data/stocks/stocks_singapore.csv
market_tickers/data/stocks/stocks_south_korea.csv
market_tickers/data/stocks/stocks_spain.csv
market_tickers/data/stocks/stocks_sweden.csv
market_tickers/data/stocks/stocks_switzerland.csv
market_tickers/data/stocks/stocks_taiwan.csv
market_tickers/data/stocks/stocks_thailand.csv
market_tickers/data/stocks/stocks_turkey.csv
market_tickers-0.3.5.dist-info/licenses/LICENSE
market_tickers-0.3.5.dist-info/METADATA
market_tickers-0.3.5.dist-info/WHEEL
market_tickers-0.3.5.dist-info/top_level.txt
market_tickers-0.3.5.dist-info/RECORD
