Metadata-Version: 2.4
Name: market-tickers
Version: 0.3.5
Summary: Human-friendly stock and index names to Yahoo Finance tickers
Author: Vedant Wade
License: MIT
Project-URL: Homepage, https://github.com/Pr3sencX/market-tickers
Requires-Python: >=3.9
License-File: LICENSE
Dynamic: license-file
